crystrat/__init__.py
crystrat/cli/main.py
crystrat/connect/crypto_com/__init__.py
crystrat/connect/crypto_com/constants.py
crystrat/connect/crypto_com/orderbook_service.py
crystrat/connect/crypto_com/rest.py
crystrat/connect/crypto_com/ws_market.py
crystrat/exec/api.py
crystrat/exec/local_oms.py
crystrat/exec/models.py
crystrat/exec/paper_broker.py
crystrat/exec/risk.py
crystrat/exec/router.py
crystrat/infra/config.py
crystrat/infra/event_bus.py
crystrat/infra/logging.py
crystrat/infra/metrics.py
crystrat/marketdata/ohlcv.py
crystrat/marketdata/runtime.py
crystrat/models/base.py
crystrat/models/orderbook.py
crystrat/strategy/base.py
crystrat/strategy/loader.py
crystrat-0.0.1.dist-info/METADATA
crystrat-0.0.1.dist-info/WHEEL
crystrat-0.0.1.dist-info/entry_points.txt
crystrat-0.0.1.dist-info/RECORD
