Metadata-Version: 2.4
Name: crystrat
Version: 0.0.1
Summary: Ultra-clean, fast, and safe live trading framework for complex crypto strategies.
Author: Crystrat Team
License: Proprietary
Requires-Python: >=3.10
Requires-Dist: aiohttp>=3.9
Requires-Dist: pydantic>=2.6
Requires-Dist: pyyaml>=6.0.1
